Metadata-Version: 1.2
Name: python-scripting
Version: 0.1.0
Summary: Boilerplate for Python scripting
Home-page: https://github.com/noahcgreen/python-scripting
Author: Noah Green
Author-email: noahc.green@icloud.com
License: MIT
Platform: UNKNOWN
Requires-Python: ~=3.6
